gwosc/__init__.py
gwosc/_version.py
gwosc/datasets.py
gwosc/locate.py
gwosc/timeline.py
gwosc/urls.py
gwosc/utils.py
gwosc/api/__init__.py
gwosc/api/v1.py
gwosc/api/v2.py
gwosc/tests/__init__.py
gwosc/tests/conftest.py
gwosc/tests/test_apiv1.py
gwosc/tests/test_apiv2.py
gwosc/tests/test_datasets.py
gwosc/tests/test_locate.py
gwosc/tests/test_timeline.py
gwosc/tests/test_urls.py
gwosc/tests/test_utils.py
gwosc-0.8.1.dist-info/licenses/LICENSE
gwosc-0.8.1.dist-info/METADATA
gwosc-0.8.1.dist-info/WHEEL
gwosc-0.8.1.dist-info/top_level.txt
gwosc-0.8.1.dist-info/RECORD
