Metadata-Version: 2.4
Name: gwosc
Version: 0.8.1
Summary: A python interface to the GW Open Science data archive
Author-email: Duncan Macleod <duncan.macleod@ligo.org>, Martin Beroiz <martin.beroiz@ligo.org>
License: MIT
Project-URL: Homepage, https://gwosc.readthedocs.io
Project-URL: Bug Tracker, https://git.ligo.org/gwosc/client/-/issues
Project-URL: Discussion Forum, https://ask.igwn.org
Project-URL: Documentation, https://gwosc.readthedocs.io
Project-URL: Source Code, https://git.ligo.org/gwosc/client.git
Classifier: Development Status :: 4 - Beta
Classifier: Programming Language :: Python
Classifier: Programming Language :: Python :: 3
Classifier: Programming Language :: Python :: 3.8
Classifier: Programming Language :: Python :: 3.9
Classifier: Programming Language :: Python :: 3.10
Classifier: Programming Language :: Python :: 3.11
Classifier: Programming Language :: Python :: 3.12
Classifier: Programming Language :: Python :: 3.13
Classifier: Intended Audience :: Science/Research
Classifier: Natural Language :: English
Classifier: Topic :: Scientific/Engineering
Classifier: Topic :: Scientific/Engineering :: Astronomy
Classifier: Topic :: Scientific/Engineering :: Physics
Classifier: License :: OSI Approved :: MIT License
Requires-Python: >=3.8
License-File: LICENSE
Requires-Dist: requests>=1.0.0
Provides-Extra: test
Requires-Dist: pytest>=2.7.0; extra == "test"
Requires-Dist: pytest-cov; extra == "test"
Requires-Dist: pytest-socket; extra == "test"
Requires-Dist: requests-mock>=1.5.0; extra == "test"
Provides-Extra: docs
Requires-Dist: sphinx; extra == "docs"
Requires-Dist: sphinx-automodapi; extra == "docs"
Requires-Dist: sphinx-immaterial-igwn; extra == "docs"
Dynamic: license-file
